tardigrade/__init__.py
tardigrade-2018.1.0.dist-info/WHEEL
tardigrade-2018.1.0.dist-info/METADATA
tardigrade-2018.1.0.dist-info/RECORD
