Metadata-Version: 1.2
Name: tardigrade
Version: 2018.1.0
Summary: A thing
Home-page: https://github.com/moshez/tardigrade
License: UNKNOWN
Author: Moshe Zadka
Author-email: zadka.moshe@gmail.com
Classifier: License :: OSI Approved :: MIT License
